setup.py
contacts/__init__.py
contacts/contacts.py
contacts/ritual/__init__.py
contacts/ritual/ritual.py
ezopack.egg-info/PKG-INFO
ezopack.egg-info/SOURCES.txt
ezopack.egg-info/dependency_links.txt
ezopack.egg-info/top_level.txt