Metadata-Version: 1.0
Name: ezopack
Version: 0.1.1
Summary: Ezoterick site
Home-page: UNKNOWN
Author: Ravend
Author-email: ravend6@gmail.com
License: UNKNOWN
Platform: UNKNOWN
